Metadata-Version: 1.1
Name: pro-clash
Version: 0.42
Summary: Processing PRO-CLASH experiments results
Home-page: http://github.com/asafpr/pro_clash
Author: Asaf Peer
Author-email: asafpr@gmail.com
License: MIT
Platform: UNKNOWN
Classifier: Development Status :: 3 - Alpha
Classifier: License :: OSI Approved :: MIT License
Classifier: Programming Language :: Python :: 2.7
Classifier: Topic :: Scientific/Engineering :: Bio-Informatics
